LICENSE
MANIFEST.in
README.md
setup.cfg
setup.py
asyncviews/__init__.py
asyncviews/base.py
asyncviews/helpers.py
asyncviews/urls.py
asyncviews/views.py
asyncviews/templates/async/base.inc.html
asyncviews/templates/async/base.inc.js
asyncviews/templates/async/error.inc.html
asyncviews/templates/async/include.inc.html
asyncviews/templates/async/placeholder.inc.html
asyncviews/templatetags/__init__.py
asyncviews/templatetags/asyncviews.py
django_asyncviews.egg-info/PKG-INFO
django_asyncviews.egg-info/SOURCES.txt
django_asyncviews.egg-info/dependency_links.txt
django_asyncviews.egg-info/not-zip-safe
django_asyncviews.egg-info/top_level.txt