Metadata-Version: 1.1
Name: django-asyncviews
Version: 0.1.0
Summary: Asynchronous JSON/HTML view library
Home-page: https://git.steadman.io/podiant/django-asyncviews
Author: Mark Steadman
Author-email: mark@podiant.co
License: MIT
Keywords: django-asyncviews
Platform: UNKNOWN
Classifier: Development Status :: 3 - Alpha
Classifier: Framework :: Django :: 1.11
Classifier: Intended Audience :: Developers
Classifier: License :: OSI Approved :: BSD License
Classifier: Natural Language :: English
Classifier: Programming Language :: Python :: 3
Classifier: Programming Language :: Python :: 3.4
Classifier: Programming Language :: Python :: 3.5
Classifier: Programming Language :: Python :: 3.6
